 {
	"status": "0",
	"msg": "ok",
	"result": {
		"number": "471799413917",
		"type": "sfexpress",
		"list": [
			{
				"time": "2016-04-13 13:30:30",
				"status": "在官网\"运单资料签收图\"可查看签收人信息"
			},
			{
				"time": "2016-04-13 13:29:36",
				"status": "已签收,感谢使用顺丰,期待再次为您服务"
			},
			{
				"time": "2016-04-13 12:53:37",
				"status": "正在派送途中(派件人:徐程得,电话:15990107893)"
			},
			{
				"time": "2016-04-13 12:41:42",
				"status": "快件到达 【杭州西湖国力大酒店营业点】"
			},
			{
				"time": "2016-04-13 10:07:50",
				"status": "快件离开【杭州总集散中心】,正发往 【杭州西湖国力大酒店营业点】"
			},
			{
				"time": "2016-04-13 05:34:33",
				"status": "快件到达 【杭州总集散中心】"
			},
			{
				"time": "2016-04-13 00:13:51",
				"status": "快件离开【北京首都机场集散中心2】,正发往下一站"
			},
			{
				"time": "2016-04-12 21:49:33",
				"status": "快件到达 【北京首都机场集散中心2】"
			},
			{
				"time": "2016-04-12 20:32:03",
				"status": "快件离开【北京东城俊景苑小区营业点】,正发往 【北京首都机场集散中心2】"
			},
			{
				"time": "2016-04-12 19:44:40",
				"status": "顺丰速运 已收取快件"
			}
		],
		"deliverystatus": "3",
		"issign": "1"
	}
}

